libCBDetect/Checkerboard.cp310-win_amd64.pyd
libCBDetect/__init__.py
libcbdetect-1.0.0.dist-info/DELVEWHEEL
libcbdetect-1.0.0.dist-info/METADATA
libcbdetect-1.0.0.dist-info/RECORD
libcbdetect-1.0.0.dist-info/WHEEL
libcbdetect-1.0.0.dist-info/licenses/LICENSE
libcbdetect.libs/concrt140-7ec2e462af9863fc63a36625cf0b5132.dll
libcbdetect.libs/msvcp140-3bb6fda0804f69805b472c303438e6c7.dll
libcbdetect.libs/opencv_world4110-3401ab4f818d41dccdb4b7e7dc8ec4fd.dll
