Metadata-Version: 2.2
Name: libCBDetect
Version: 1.0.0
Summary: Python bindings for a C++ Checkerboard detector
Author-Email: =?utf-8?q?Micha=C3=ABl_Hillen?= <michael.hillen@uantwerpen.be>
License: MIT
Classifier: Programming Language :: Python :: 3
Classifier: Programming Language :: C++
Classifier: License :: OSI Approved :: MIT License
Classifier: Operating System :: OS Independent
Project-URL: Homepage, https://github.com/InViLabUAntwerp/libCBDetect
Requires-Python: >=3.10
Requires-Dist: numpy<1.29.0,>=1.22.4
Requires-Dist: opencv-python-headless
